dstulz/__init__.py
dstulz/dstulz.py
dstulz-0.1.0.dist-info/METADATA
dstulz-0.1.0.dist-info/WHEEL
dstulz-0.1.0.dist-info/RECORD
