Metadata-Version: 2.1
Name: dstulz
Version: 0.1.0
Summary: Set of tools for data science
License: MIT
Author: Siarhei Uhlianets
Author-email: s.uhlianets@gmail.com
Requires-Python: >=3.11,<4.0
Classifier: License :: OSI Approved :: MIT License
Classifier: Programming Language :: Python :: 3
Classifier: Programming Language :: Python :: 3.11
Classifier: Programming Language :: Python :: 3.12
Requires-Dist: numpy (>=1.26.4,<2.0.0)
